{"time":1586422207,"temperature":15,"contents":[{"theta":0,"phi":0,"value":275},{"theta":90,"phi":180,"value":140},{"theta":10,"phi":0,"value":258},{"theta":80,"phi":180,"value":149},{"theta":20,"phi":0,"value":241},{"theta":70,"phi":180,"value":175},{"theta":30,"phi":0,"value":243},{"theta":60,"phi":180,"value":195},{"theta":40,"phi":0,"value":204},{"theta":50,"phi":180,"value":184},{"theta":50,"phi":0,"value":182},{"theta":40,"phi":180,"value":216},{"theta":60,"phi":0,"value":200},{"theta":30,"phi":180,"value":266},{"theta":70,"phi":0,"value":151},{"theta":20,"phi":180,"value":268},{"theta":80,"phi":0,"value":139},{"theta":10,"phi":180,"value":276},{"theta":90,"phi":0,"value":116},{"theta":0,"phi":180,"value":268},{"theta":0,"phi":20,"value":270},{"theta":90,"phi":200,"value":137},{"theta":10,"phi":20,"value":348},{"theta":80,"phi":200,"value":228},{"theta":20,"phi":20,"value":243},{"theta":70,"phi":200,"value":167},{"theta":30,"phi":20,"value":214},{"theta":60,"phi":200,"value":173},{"theta":40,"phi":20,"value":209},{"theta":50,"phi":200,"value":182},{"theta":50,"phi":20,"value":195},{"theta":40,"phi":200,"value":206},{"theta":60,"phi":20,"value":161},{"theta":30,"phi":200,"value":220},{"theta":70,"phi":20,"value":167},{"theta":20,"phi":200,"value":262},{"theta":80,"phi":20,"value":149},{"theta":10,"phi":200,"value":266},{"theta":90,"phi":20,"value":120},{"theta":0,"phi":200,"value":278},{"theta":0,"phi":40,"value":262},{"theta":90,"phi":220,"value":131},{"theta":10,"phi":40,"value":264},{"theta":80,"phi":220,"value":140},{"theta":20,"phi":40,"value":254},{"theta":70,"phi":220,"value":157},{"theta":30,"phi":40,"value":219},{"theta":60,"phi":220,"value":164},{"theta":40,"phi":40,"value":207},{"theta":50,"phi":220,"value":178},{"theta":50,"phi":40,"value":184},{"theta":40,"phi":220,"value":193},{"theta":60,"phi":40,"value":180},{"theta":30,"phi":220,"value":209},{"theta":70,"phi":40,"value":169},{"theta":20,"phi":220,"value":263},{"theta":80,"phi":40,"value":163},{"theta":10,"phi":220,"value":268},{"theta":90,"phi":40,"value":145},{"theta":0,"phi":220,"value":271},{"theta":0,"phi":60,"value":260},{"theta":90,"phi":240,"value":115},{"theta":10,"phi":60,"value":266},{"theta":80,"phi":240,"value":123},{"theta":20,"phi":60,"value":257},{"theta":70,"phi":240,"value":145},{"theta":30,"phi":60,"value":311},{"theta":60,"phi":240,"value":251},{"theta":40,"phi":60,"value":219},{"theta":50,"phi":240,"value":170},{"theta":50,"phi":60,"value":296},{"theta":40,"phi":240,"value":294},{"theta":60,"phi":60,"value":182},{"theta":30,"phi":240,"value":200},{"theta":70,"phi":60,"value":178},{"theta":20,"phi":240,"value":246},{"theta":80,"phi":60,"value":175},{"theta":10,"phi":240,"value":251},{"theta":90,"phi":60,"value":147},{"theta":0,"phi":240,"value":260},{"theta":0,"phi":80,"value":257},{"theta":90,"phi":260,"value":102},{"theta":10,"phi":80,"value":260},{"theta":80,"phi":260,"value":115},{"theta":20,"phi":80,"value":257},{"theta":70,"phi":260,"value":134},{"theta":30,"phi":80,"value":233},{"theta":60,"phi":260,"value":147},{"theta":40,"phi":80,"value":232},{"theta":50,"phi":260,"value":156},{"theta":50,"phi":80,"value":213},{"theta":40,"phi":260,"value":177},{"theta":60,"phi":80,"value":184},{"theta":30,"phi":260,"value":189},{"theta":70,"phi":80,"value":187},{"theta":20,"phi":260,"value":238},{"theta":80,"phi":80,"value":173},{"theta":10,"phi":260,"value":249},{"theta":90,"phi":80,"value":164},{"theta":0,"phi":260,"value":255},{"theta":0,"phi":100,"value":344},{"theta":90,"phi":280,"value":168},{"theta":10,"phi":100,"value":263},{"theta":80,"phi":280,"value":105},{"theta":20,"phi":100,"value":348},{"theta":70,"phi":280,"value":203},{"theta":30,"phi":100,"value":243},{"theta":60,"phi":280,"value":136},{"theta":40,"phi":100,"value":258},{"theta":50,"phi":280,"value":167},{"theta":50,"phi":100,"value":223},{"theta":40,"phi":280,"value":163},{"theta":60,"phi":100,"value":196},{"theta":30,"phi":280,"value":183},{"theta":70,"phi":100,"value":199},{"theta":20,"phi":280,"value":230},{"theta":80,"phi":100,"value":186},{"theta":10,"phi":280,"value":250},{"theta":90,"phi":100,"value":168},{"theta":0,"phi":280,"value":258},{"theta":0,"phi":120,"value":254},{"theta":90,"phi":300,"value":85},{"theta":10,"phi":120,"value":260},{"theta":80,"phi":300,"value":94},{"theta":20,"phi":120,"value":264},{"theta":70,"phi":300,"value":115},{"theta":30,"phi":120,"value":249},{"theta":60,"phi":300,"value":126},{"theta":40,"phi":120,"value":244},{"theta":50,"phi":300,"value":136},{"theta":50,"phi":120,"value":217},{"theta":40,"phi":300,"value":159},{"theta":60,"phi":120,"value":220},{"theta":30,"phi":300,"value":222},{"theta":70,"phi":120,"value":200},{"theta":20,"phi":300,"value":230},{"theta":80,"phi":120,"value":181},{"theta":10,"phi":300,"value":237},{"theta":90,"phi":120,"value":213},{"theta":0,"phi":300,"value":321},{"theta":0,"phi":140,"value":251},{"theta":90,"phi":320,"value":91},{"theta":10,"phi":140,"value":259},{"theta":80,"phi":320,"value":96},{"theta":20,"phi":140,"value":317},{"theta":70,"phi":320,"value":163},{"theta":30,"phi":140,"value":255},{"theta":60,"phi":320,"value":163},{"theta":40,"phi":140,"value":235},{"theta":50,"phi":320,"value":133},{"theta":50,"phi":140,"value":328},{"theta":40,"phi":320,"value":250},{"theta":60,"phi":140,"value":200},{"theta":30,"phi":320,"value":175},{"theta":70,"phi":140,"value":202},{"theta":20,"phi":320,"value":219},{"theta":80,"phi":140,"value":247},{"theta":10,"phi":320,"value":277},{"theta":90,"phi":140,"value":166},{"theta":0,"phi":320,"value":252},{"theta":0,"phi":160,"value":246},{"theta":90,"phi":340,"value":87},{"theta":10,"phi":160,"value":249},{"theta":80,"phi":340,"value":101},{"theta":20,"phi":160,"value":259},{"theta":70,"phi":340,"value":144},{"theta":30,"phi":160,"value":293},{"theta":60,"phi":340,"value":158},{"theta":40,"phi":160,"value":234},{"theta":50,"phi":340,"value":134},{"theta":50,"phi":160,"value":211},{"theta":40,"phi":340,"value":156},{"theta":60,"phi":160,"value":196},{"theta":30,"phi":340,"value":170},{"theta":70,"phi":160,"value":191},{"theta":20,"phi":340,"value":221},{"theta":80,"phi":160,"value":176},{"theta":10,"phi":340,"value":235},{"theta":90,"phi":160,"value":164},{"theta":0,"phi":340,"value":239}]}