{"time":1586160010,"temperature":18.19,"contents":[{"theta":0,"phi":0,"value":1767},{"theta":90,"phi":180,"value":1713},{"theta":10,"phi":0,"value":1633},{"theta":80,"phi":180,"value":1808},{"theta":20,"phi":0,"value":1470},{"theta":70,"phi":180,"value":1935},{"theta":30,"phi":0,"value":1255},{"theta":60,"phi":180,"value":1745},{"theta":40,"phi":0,"value":1175},{"theta":50,"phi":180,"value":1798},{"theta":50,"phi":0,"value":1055},{"theta":40,"phi":180,"value":1852},{"theta":60,"phi":0,"value":983},{"theta":30,"phi":180,"value":1876},{"theta":70,"phi":0,"value":1040},{"theta":20,"phi":180,"value":2015},{"theta":80,"phi":0,"value":992},{"theta":10,"phi":180,"value":1958},{"theta":90,"phi":0,"value":975},{"theta":0,"phi":180,"value":1791},{"theta":0,"phi":20,"value":1759},{"theta":90,"phi":200,"value":1716},{"theta":10,"phi":20,"value":1655},{"theta":80,"phi":200,"value":1791},{"theta":20,"phi":20,"value":1486},{"theta":70,"phi":200,"value":1928},{"theta":30,"phi":20,"value":1271},{"theta":60,"phi":200,"value":1772},{"theta":40,"phi":20,"value":1203},{"theta":50,"phi":200,"value":1791},{"theta":50,"phi":20,"value":1095},{"theta":40,"phi":200,"value":1880},{"theta":60,"phi":20,"value":1017},{"theta":30,"phi":200,"value":1892},{"theta":70,"phi":20,"value":1100},{"theta":20,"phi":200,"value":2078},{"theta":80,"phi":20,"value":1031},{"theta":10,"phi":200,"value":1976},{"theta":90,"phi":20,"value":951},{"theta":0,"phi":200,"value":1816},{"theta":0,"phi":40,"value":1832},{"theta":90,"phi":220,"value":1734},{"theta":10,"phi":40,"value":1678},{"theta":80,"phi":220,"value":1755},{"theta":20,"phi":40,"value":1648},{"theta":70,"phi":220,"value":1930},{"theta":30,"phi":40,"value":1300},{"theta":60,"phi":220,"value":1751},{"theta":40,"phi":40,"value":1271},{"theta":50,"phi":220,"value":1825},{"theta":50,"phi":40,"value":1164},{"theta":40,"phi":220,"value":1839},{"theta":60,"phi":40,"value":1059},{"theta":30,"phi":220,"value":1851},{"theta":70,"phi":40,"value":1119},{"theta":20,"phi":220,"value":2000},{"theta":80,"phi":40,"value":1065},{"theta":10,"phi":220,"value":1936},{"theta":90,"phi":40,"value":999},{"theta":0,"phi":220,"value":1840},{"theta":0,"phi":60,"value":1795},{"theta":90,"phi":240,"value":1453},{"theta":10,"phi":60,"value":1751},{"theta":80,"phi":240,"value":1496},{"theta":20,"phi":60,"value":1635},{"theta":70,"phi":240,"value":1680},{"theta":30,"phi":60,"value":1391},{"theta":60,"phi":240,"value":1711},{"theta":40,"phi":60,"value":1302},{"theta":50,"phi":240,"value":1667},{"theta":50,"phi":60,"value":1344},{"theta":40,"phi":240,"value":1843},{"theta":60,"phi":60,"value":1107},{"theta":30,"phi":240,"value":1743},{"theta":70,"phi":60,"value":1168},{"theta":20,"phi":240,"value":1934},{"theta":80,"phi":60,"value":1112},{"theta":10,"phi":240,"value":1896},{"theta":90,"phi":60,"value":1017},{"theta":0,"phi":240,"value":1799},{"theta":0,"phi":80,"value":1820},{"theta":90,"phi":260,"value":1119},{"theta":10,"phi":80,"value":1824},{"theta":80,"phi":260,"value":1201},{"theta":20,"phi":80,"value":1702},{"theta":70,"phi":260,"value":1303},{"theta":30,"phi":80,"value":1452},{"theta":60,"phi":260,"value":1375},{"theta":40,"phi":80,"value":1439},{"theta":50,"phi":260,"value":1447},{"theta":50,"phi":80,"value":1285},{"theta":40,"phi":260,"value":1521},{"theta":60,"phi":80,"value":1192},{"theta":30,"phi":260,"value":1596},{"theta":70,"phi":80,"value":1246},{"theta":20,"phi":260,"value":1830},{"theta":80,"phi":80,"value":1167},{"theta":10,"phi":260,"value":1840},{"theta":90,"phi":80,"value":1099},{"theta":0,"phi":260,"value":1824},{"theta":0,"phi":100,"value":1889},{"theta":90,"phi":280,"value":992},{"theta":10,"phi":100,"value":1807},{"theta":80,"phi":280,"value":984},{"theta":20,"phi":100,"value":1919},{"theta":70,"phi":280,"value":1118},{"theta":30,"phi":100,"value":1592},{"theta":60,"phi":280,"value":1154},{"theta":40,"phi":100,"value":1544},{"theta":50,"phi":280,"value":1224},{"theta":50,"phi":100,"value":1503},{"theta":40,"phi":280,"value":1347},{"theta":60,"phi":100,"value":1327},{"theta":30,"phi":280,"value":1407},{"theta":70,"phi":100,"value":1399},{"theta":20,"phi":280,"value":1744},{"theta":80,"phi":100,"value":1352},{"theta":10,"phi":280,"value":1788},{"theta":90,"phi":100,"value":1183},{"theta":0,"phi":280,"value":1832},{"theta":0,"phi":120,"value":1840},{"theta":90,"phi":300,"value":832},{"theta":10,"phi":120,"value":1883},{"theta":80,"phi":300,"value":883},{"theta":20,"phi":120,"value":1895},{"theta":70,"phi":300,"value":958},{"theta":30,"phi":120,"value":1735},{"theta":60,"phi":300,"value":971},{"theta":40,"phi":120,"value":1728},{"theta":50,"phi":300,"value":1019},{"theta":50,"phi":120,"value":1699},{"theta":40,"phi":300,"value":1187},{"theta":60,"phi":120,"value":1572},{"theta":30,"phi":300,"value":1251},{"theta":70,"phi":120,"value":1668},{"theta":20,"phi":300,"value":1639},{"theta":80,"phi":120,"value":1560},{"theta":10,"phi":300,"value":1739},{"theta":90,"phi":120,"value":1536},{"theta":0,"phi":300,"value":1864},{"theta":0,"phi":140,"value":1855},{"theta":90,"phi":320,"value":819},{"theta":10,"phi":140,"value":1927},{"theta":80,"phi":320,"value":867},{"theta":20,"phi":140,"value":1967},{"theta":70,"phi":320,"value":909},{"theta":30,"phi":140,"value":1906},{"theta":60,"phi":320,"value":899},{"theta":40,"phi":140,"value":1896},{"theta":50,"phi":320,"value":955},{"theta":50,"phi":140,"value":1847},{"theta":40,"phi":320,"value":1052},{"theta":60,"phi":140,"value":1775},{"theta":30,"phi":320,"value":1176},{"theta":70,"phi":140,"value":1927},{"theta":20,"phi":320,"value":1559},{"theta":80,"phi":140,"value":1927},{"theta":10,"phi":320,"value":1671},{"theta":90,"phi":140,"value":1704},{"theta":0,"phi":320,"value":1820},{"theta":0,"phi":160,"value":1855},{"theta":90,"phi":340,"value":841},{"theta":10,"phi":160,"value":1944},{"theta":80,"phi":340,"value":888},{"theta":20,"phi":160,"value":2036},{"theta":70,"phi":340,"value":929},{"theta":30,"phi":160,"value":2015},{"theta":60,"phi":340,"value":889},{"theta":40,"phi":160,"value":2014},{"theta":50,"phi":340,"value":939},{"theta":50,"phi":160,"value":1967},{"theta":40,"phi":340,"value":1027},{"theta":60,"phi":160,"value":1928},{"theta":30,"phi":340,"value":1150},{"theta":70,"phi":160,"value":2112},{"theta":20,"phi":340,"value":1511},{"theta":80,"phi":160,"value":2081},{"theta":10,"phi":340,"value":1710},{"theta":90,"phi":160,"value":1932},{"theta":0,"phi":340,"value":1783}]}