{"time":1596442203,"temperature":35,"contents":[{"theta":0,"phi":0,"value":2684},{"theta":90,"phi":180,"value":2727},{"theta":10,"phi":0,"value":2680},{"theta":80,"phi":180,"value":2720},{"theta":20,"phi":0,"value":2691},{"theta":70,"phi":180,"value":2723},{"theta":30,"phi":0,"value":2159},{"theta":60,"phi":180,"value":2731},{"theta":40,"phi":0,"value":2155},{"theta":50,"phi":180,"value":2728},{"theta":50,"phi":0,"value":2147},{"theta":40,"phi":180,"value":2734},{"theta":60,"phi":0,"value":2145},{"theta":30,"phi":180,"value":2735},{"theta":70,"phi":0,"value":2302},{"theta":20,"phi":180,"value":2680},{"theta":80,"phi":0,"value":2305},{"theta":10,"phi":180,"value":2675},{"theta":90,"phi":0,"value":2296},{"theta":0,"phi":180,"value":2689},{"theta":0,"phi":20,"value":2674},{"theta":90,"phi":200,"value":2708},{"theta":10,"phi":20,"value":2691},{"theta":80,"phi":200,"value":2691},{"theta":20,"phi":20,"value":2677},{"theta":70,"phi":200,"value":2715},{"theta":30,"phi":20,"value":2147},{"theta":60,"phi":200,"value":2720},{"theta":40,"phi":20,"value":2156},{"theta":50,"phi":200,"value":2722},{"theta":50,"phi":20,"value":2143},{"theta":40,"phi":200,"value":2724},{"theta":60,"phi":20,"value":2143},{"theta":30,"phi":200,"value":2727},{"theta":70,"phi":20,"value":2301},{"theta":20,"phi":200,"value":2679},{"theta":80,"phi":20,"value":2291},{"theta":10,"phi":200,"value":2675},{"theta":90,"phi":20,"value":2279},{"theta":0,"phi":200,"value":2664},{"theta":0,"phi":40,"value":2663},{"theta":90,"phi":220,"value":2706},{"theta":10,"phi":40,"value":2689},{"theta":80,"phi":220,"value":2715},{"theta":20,"phi":40,"value":2670},{"theta":70,"phi":220,"value":2715},{"theta":30,"phi":40,"value":2143},{"theta":60,"phi":220,"value":2713},{"theta":40,"phi":40,"value":2140},{"theta":50,"phi":220,"value":2719},{"theta":50,"phi":40,"value":2143},{"theta":40,"phi":220,"value":2720},{"theta":60,"phi":40,"value":2159},{"theta":30,"phi":220,"value":2723},{"theta":70,"phi":40,"value":2275},{"theta":20,"phi":220,"value":2671},{"theta":80,"phi":40,"value":2287},{"theta":10,"phi":220,"value":2671},{"theta":90,"phi":40,"value":2285},{"theta":0,"phi":220,"value":2671},{"theta":0,"phi":60,"value":2688},{"theta":90,"phi":240,"value":2704},{"theta":10,"phi":60,"value":2688},{"theta":80,"phi":240,"value":2715},{"theta":20,"phi":60,"value":2680},{"theta":70,"phi":240,"value":2711},{"theta":30,"phi":60,"value":2147},{"theta":60,"phi":240,"value":2723},{"theta":40,"phi":60,"value":2147},{"theta":50,"phi":240,"value":2723},{"theta":50,"phi":60,"value":2150},{"theta":40,"phi":240,"value":2725},{"theta":60,"phi":60,"value":2144},{"theta":30,"phi":240,"value":2719},{"theta":70,"phi":60,"value":2279},{"theta":20,"phi":240,"value":2679},{"theta":80,"phi":60,"value":2280},{"theta":10,"phi":240,"value":2672},{"theta":90,"phi":60,"value":2275},{"theta":0,"phi":240,"value":2677},{"theta":0,"phi":80,"value":2674},{"theta":90,"phi":260,"value":2714},{"theta":10,"phi":80,"value":2679},{"theta":80,"phi":260,"value":2704},{"theta":20,"phi":80,"value":2671},{"theta":70,"phi":260,"value":2704},{"theta":30,"phi":80,"value":2203},{"theta":60,"phi":260,"value":2719},{"theta":40,"phi":80,"value":2145},{"theta":50,"phi":260,"value":2715},{"theta":50,"phi":80,"value":2147},{"theta":40,"phi":260,"value":2721},{"theta":60,"phi":80,"value":2157},{"theta":30,"phi":260,"value":2719},{"theta":70,"phi":80,"value":2289},{"theta":20,"phi":260,"value":2683},{"theta":80,"phi":80,"value":2295},{"theta":10,"phi":260,"value":2683},{"theta":90,"phi":80,"value":2294},{"theta":0,"phi":260,"value":2671},{"theta":0,"phi":100,"value":2693},{"theta":90,"phi":280,"value":2715},{"theta":10,"phi":100,"value":2703},{"theta":80,"phi":280,"value":2735},{"theta":20,"phi":100,"value":2686},{"theta":70,"phi":280,"value":2725},{"theta":30,"phi":100,"value":2160},{"theta":60,"phi":280,"value":2727},{"theta":40,"phi":100,"value":2207},{"theta":50,"phi":280,"value":2711},{"theta":50,"phi":100,"value":2162},{"theta":40,"phi":280,"value":2724},{"theta":60,"phi":100,"value":2160},{"theta":30,"phi":280,"value":2724},{"theta":70,"phi":100,"value":2310},{"theta":20,"phi":280,"value":2687},{"theta":80,"phi":100,"value":2302},{"theta":10,"phi":280,"value":2696},{"theta":90,"phi":100,"value":2311},{"theta":0,"phi":280,"value":2700},{"theta":0,"phi":120,"value":2695},{"theta":90,"phi":300,"value":2716},{"theta":10,"phi":120,"value":2695},{"theta":80,"phi":300,"value":2718},{"theta":20,"phi":120,"value":2699},{"theta":70,"phi":300,"value":2717},{"theta":30,"phi":120,"value":2177},{"theta":60,"phi":300,"value":2726},{"theta":40,"phi":120,"value":2159},{"theta":50,"phi":300,"value":2727},{"theta":50,"phi":120,"value":2179},{"theta":40,"phi":300,"value":2728},{"theta":60,"phi":120,"value":2163},{"theta":30,"phi":300,"value":2721},{"theta":70,"phi":120,"value":2311},{"theta":20,"phi":300,"value":2694},{"theta":80,"phi":120,"value":2331},{"theta":10,"phi":300,"value":2695},{"theta":90,"phi":120,"value":2311},{"theta":0,"phi":300,"value":2686},{"theta":0,"phi":140,"value":2656},{"theta":90,"phi":320,"value":2688},{"theta":10,"phi":140,"value":2657},{"theta":80,"phi":320,"value":2680},{"theta":20,"phi":140,"value":2659},{"theta":70,"phi":320,"value":2683},{"theta":30,"phi":140,"value":2316},{"theta":60,"phi":320,"value":2694},{"theta":40,"phi":140,"value":2143},{"theta":50,"phi":320,"value":2715},{"theta":50,"phi":140,"value":2143},{"theta":40,"phi":320,"value":2709},{"theta":60,"phi":140,"value":2143},{"theta":30,"phi":320,"value":2710},{"theta":70,"phi":140,"value":2305},{"theta":20,"phi":320,"value":2671},{"theta":80,"phi":140,"value":2303},{"theta":10,"phi":320,"value":2668},{"theta":90,"phi":140,"value":2305},{"theta":0,"phi":320,"value":2665},{"theta":0,"phi":160,"value":2686},{"theta":90,"phi":340,"value":2703},{"theta":10,"phi":160,"value":2691},{"theta":80,"phi":340,"value":2704},{"theta":20,"phi":160,"value":2691},{"theta":70,"phi":340,"value":2703},{"theta":30,"phi":160,"value":2155},{"theta":60,"phi":340,"value":2719},{"theta":40,"phi":160,"value":2220},{"theta":50,"phi":340,"value":2703},{"theta":50,"phi":160,"value":2144},{"theta":40,"phi":340,"value":2707},{"theta":60,"phi":160,"value":2144},{"theta":30,"phi":340,"value":2715},{"theta":70,"phi":160,"value":2303},{"theta":20,"phi":340,"value":2681},{"theta":80,"phi":160,"value":2296},{"theta":10,"phi":340,"value":2673},{"theta":90,"phi":160,"value":2295},{"theta":0,"phi":340,"value":2683}]}